shitpost/__init__.py
shitpost/callback.py
shitpost/handler.py
shitpost-1.0.0.dist-info/LICENSE
shitpost-1.0.0.dist-info/METADATA
shitpost-1.0.0.dist-info/WHEEL
shitpost-1.0.0.dist-info/RECORD
