Metadata-Version: 2.1
Name: shitpost
Version: 1.0.0
Summary: 
License: MIT
Author: TAG-Epic
Author-email: tagepicuwu@gmail.com
Requires-Python: >=3.8,<4.0
Classifier: License :: OSI Approved :: MIT License
Classifier: Programming Language :: Python :: 3
Classifier: Programming Language :: Python :: 3.8
Classifier: Programming Language :: Python :: 3.9
Classifier: Programming Language :: Python :: 3.10
Classifier: Programming Language :: Python :: 3.11
Classifier: Programming Language :: Python :: 3.12
Requires-Dist: nextcore (>=2.0.0,<3.0.0)
Requires-Dist: parse (>=1.19.0,<2.0.0)
